{"frames": {

"Pixel_Knight_Attack0.png":
{
	"frame": {"x":0,"y":0,"w":42,"h":64},
	"rotated": false,
	"trimmed": false,
	"spriteSourceSize": {"x":0,"y":0,"w":42,"h":64},
	"sourceSize": {"w":42,"h":64},
	"anchor": {"x":0.5,"y":0.5}
},
"Pixel_Knight_Attack1.png":
{
	"frame": {"x":42,"y":0,"w":42,"h":64},
	"rotated": false,
	"trimmed": false,
	"spriteSourceSize": {"x":0,"y":0,"w":42,"h":64},
	"sourceSize": {"w":42,"h":64},
	"anchor": {"x":0.5,"y":0.5}
},
"Pixel_Knight_Attack2.png":
{
	"frame": {"x":84,"y":0,"w":42,"h":64},
	"rotated": false,
	"trimmed": false,
	"spriteSourceSize": {"x":0,"y":0,"w":42,"h":64},
	"sourceSize": {"w":42,"h":64},
	"anchor": {"x":0.5,"y":0.5}
},
"Pixel_Knight_Attack3.png":
{
	"frame": {"x":126,"y":0,"w":42,"h":64},
	"rotated": false,
	"trimmed": false,
	"spriteSourceSize": {"x":0,"y":0,"w":42,"h":64},
	"sourceSize": {"w":42,"h":64},
	"anchor": {"x":0.5,"y":0.5}
},
"Pixel_Knight_Attack4.png":
{
	"frame": {"x":168,"y":0,"w":42,"h":64},
	"rotated": false,
	"trimmed": false,
	"spriteSourceSize": {"x":0,"y":0,"w":42,"h":64},
	"sourceSize": {"w":42,"h":64},
	"anchor": {"x":0.5,"y":0.5}
},
"Pixel_Knight_Attack5.png":
{
	"frame": {"x":210,"y":0,"w":42,"h":64},
	"rotated": false,
	"trimmed": false,
	"spriteSourceSize": {"x":0,"y":0,"w":42,"h":64},
	"sourceSize": {"w":42,"h":64},
	"anchor": {"x":0.5,"y":0.5}
},
"Pixel_Knight_Idle0.png":
{
	"frame": {"x":252,"y":0,"w":44,"h":64},
	"rotated": false,
	"trimmed": false,
	"spriteSourceSize": {"x":0,"y":0,"w":44,"h":64},
	"sourceSize": {"w":44,"h":64},
	"anchor": {"x":0.5,"y":0.5}
},
"Pixel_Knight_Idle1.png":
{
	"frame": {"x":296,"y":0,"w":44,"h":64},
	"rotated": false,
	"trimmed": false,
	"spriteSourceSize": {"x":0,"y":0,"w":44,"h":64},
	"sourceSize": {"w":44,"h":64},
	"anchor": {"x":0.5,"y":0.5}
},
"Pixel_Knight_Idle2.png":
{
	"frame": {"x":340,"y":0,"w":44,"h":64},
	"rotated": false,
	"trimmed": false,
	"spriteSourceSize": {"x":0,"y":0,"w":44,"h":64},
	"sourceSize": {"w":44,"h":64},
	"anchor": {"x":0.5,"y":0.5}
},
"Pixel_Knight_Idle3.png":
{
	"frame": {"x":384,"y":0,"w":44,"h":64},
	"rotated": false,
	"trimmed": false,
	"spriteSourceSize": {"x":0,"y":0,"w":44,"h":64},
	"sourceSize": {"w":44,"h":64},
	"anchor": {"x":0.5,"y":0.5}
},
"Pixel_Knight_Idle4.png":
{
	"frame": {"x":428,"y":0,"w":44,"h":64},
	"rotated": false,
	"trimmed": false,
	"spriteSourceSize": {"x":0,"y":0,"w":44,"h":64},
	"sourceSize": {"w":44,"h":64},
	"anchor": {"x":0.5,"y":0.5}
},
"Pixel_Knight_Idle5.png":
{
	"frame": {"x":472,"y":0,"w":44,"h":64},
	"rotated": false,
	"trimmed": false,
	"spriteSourceSize": {"x":0,"y":0,"w":44,"h":64},
	"sourceSize": {"w":44,"h":64},
	"anchor": {"x":0.5,"y":0.5}
},
"Pixel_Knight_Idle6.png":
{
	"frame": {"x":516,"y":0,"w":44,"h":64},
	"rotated": false,
	"trimmed": false,
	"spriteSourceSize": {"x":0,"y":0,"w":44,"h":64},
	"sourceSize": {"w":44,"h":64},
	"anchor": {"x":0.5,"y":0.5}
},
"Pixel_Knight_Idle7.png":
{
	"frame": {"x":560,"y":0,"w":44,"h":64},
	"rotated": false,
	"trimmed": false,
	"spriteSourceSize": {"x":0,"y":0,"w":44,"h":64},
	"sourceSize": {"w":44,"h":64},
	"anchor": {"x":0.5,"y":0.5}
},
"Pixel_Knight_Idle8.png":
{
	"frame": {"x":604,"y":0,"w":44,"h":64},
	"rotated": false,
	"trimmed": false,
	"spriteSourceSize": {"x":0,"y":0,"w":44,"h":64},
	"sourceSize": {"w":44,"h":64},
	"anchor": {"x":0.5,"y":0.5}
},
"Pixel_Knight_Idle9.png":
{
	"frame": {"x":648,"y":0,"w":44,"h":64},
	"rotated": false,
	"trimmed": false,
	"spriteSourceSize": {"x":0,"y":0,"w":44,"h":64},
	"sourceSize": {"w":44,"h":64},
	"anchor": {"x":0.5,"y":0.5}
},
"Pixel_Knight_Walk0.png":
{
	"frame": {"x":692,"y":0,"w":42,"h":64},
	"rotated": false,
	"trimmed": false,
	"spriteSourceSize": {"x":0,"y":0,"w":42,"h":64},
	"sourceSize": {"w":42,"h":64},
	"anchor": {"x":0.5,"y":0.5}
},
"Pixel_Knight_Walk1.png":
{
	"frame": {"x":734,"y":0,"w":42,"h":64},
	"rotated": false,
	"trimmed": false,
	"spriteSourceSize": {"x":0,"y":0,"w":42,"h":64},
	"sourceSize": {"w":42,"h":64},
	"anchor": {"x":0.5,"y":0.5}
},
"Pixel_Knight_Walk2.png":
{
	"frame": {"x":776,"y":0,"w":42,"h":64},
	"rotated": false,
	"trimmed": false,
	"spriteSourceSize": {"x":0,"y":0,"w":42,"h":64},
	"sourceSize": {"w":42,"h":64},
	"anchor": {"x":0.5,"y":0.5}
},
"Pixel_Knight_Walk3.png":
{
	"frame": {"x":818,"y":0,"w":42,"h":64},
	"rotated": false,
	"trimmed": false,
	"spriteSourceSize": {"x":0,"y":0,"w":42,"h":64},
	"sourceSize": {"w":42,"h":64},
	"anchor": {"x":0.5,"y":0.5}
}},
"animations": {
	"Pixel_Knight_Attack": ["Pixel_Knight_Attack0.png","Pixel_Knight_Attack1.png","Pixel_Knight_Attack2.png","Pixel_Knight_Attack3.png","Pixel_Knight_Attack4.png","Pixel_Knight_Attack5.png"],
	"Pixel_Knight_Idle": ["Pixel_Knight_Idle0.png","Pixel_Knight_Idle1.png","Pixel_Knight_Idle2.png","Pixel_Knight_Idle3.png","Pixel_Knight_Idle4.png","Pixel_Knight_Idle5.png","Pixel_Knight_Idle6.png","Pixel_Knight_Idle7.png","Pixel_Knight_Idle8.png","Pixel_Knight_Idle9.png"],
	"Pixel_Knight_Walk": ["Pixel_Knight_Walk0.png","Pixel_Knight_Walk1.png","Pixel_Knight_Walk2.png","Pixel_Knight_Walk3.png"]
},
"meta": {
	"app": "https://www.codeandweb.com/texturepacker",
	"version": "1.0",
	"image": "Full_animation.png",
	"format": "RGBA8888",
	"size": {"w":860,"h":64},
	"scale": "1",
	"smartupdate": "$TexturePacker:SmartUpdate:ea97e3a02885021c454fade50a56f25c:4cd95642b59f2df8859be7151f7d869d:647262f4effee2d88a570d7e8d37cb9e$"
}
}
